phorganize/__init__.py
phorganize/main.py
phorganize-0.1.2.dist-info/METADATA
phorganize-0.1.2.dist-info/WHEEL
phorganize-0.1.2.dist-info/entry_points.txt
phorganize-0.1.2.dist-info/licenses/LICENSE
phorganize-0.1.2.dist-info/RECORD
