Metadata-Version: 2.4
Name: phorganize
Version: 0.1.2
Summary: Phorganize is a python script to organize photos and videos using embedded meta data in the files.
Project-URL: Homepage, https://github.com/rioriost/homebrew-phorganize
Project-URL: Issues, https://github.com/rioriost/homebrew-phorganize/issues
Author-email: Rio Fujita <rifujita@microsoft.com>
License: MIT License
License-File: LICENSE
Requires-Python: >=3.11
Requires-Dist: python-magic>=0.4.27
